{
  "SimpleReport": {
    "ValidationPolicy": {
      "PolicyName": "QES AdESQC TL based",
      "PolicyDescription": "Validate electronic signatures and indicates whether they are Advanced electronic Signatures (AdES), AdES supported by a Qualified Certificate (AdES/QC) or a\n\t\tQualified electronic Signature (QES). All certificates and their related chains supporting the signatures are validated against the EU Member State Trusted Lists (this includes\n\t\tsigner's certificate and certificates used to validate certificate validity status services - CRLs, OCSP, and time-stamps).\n\t"
    },
    "DocumentName": "test.pdf",
    "ValidSignaturesCount": 4,
    "SignaturesCount": 4,
    "ContainerType": null,
    "signatureOrTimestamp": [
      {
        "Signature": {
          "SigningTime": "2021-03-07T12:24:24",
          "BestSignatureTime": "2021-03-09T21:31:14",
          "SignedBy": "Test certificate Dia",
          "SignatureLevel": {
            "value": "AdESig-QC",
            "description": "Advanced Electronic Signature supported by a Qualified Certificate"
          },
          "SignatureScope": [
            {
              "value": "The document ByteRange : [0, 19800, 35850, 4921]",
              "name": "Partial PDF",
              "scope": "PARTIAL"
            }
          ],
          "Filename": null,
          "CertificateChain": {
            "Certificate": [
              {
                "id": "C-F58AC656E1F9B00EFB2293962CBB8201E3F75FDB099B52B92A67D2D8BC92BCCF",
                "qualifiedName": "Test certificate Dia"
              },
              {
                "id": "C-73B2E40CFEA79BD5CF9F6B100EC8262DE4B31499C80BD7DF12BC686C3B6F0B6B",
                "qualifiedName": "\"DIIA\". Qualified Trust Services Provider"
              },
              {
                "id": "C-944F1E01408F0FD0A20820BCB92044971E5F15AC5DC69871149BFCD0BBF3016D",
                "qualifiedName": "Central certification authority"
              }
            ]
          },
          "Indication": "TOTAL_PASSED",
          "SubIndication": null,
          "Errors": [],
          "Warnings": [
            "The private key does not reside in a QSCD at issuance time!",
            "The private key does not reside in a QSCD at (best) signing time!"
          ],
          "Infos": [],
          "Id": "S-EC27BBA27F938B7266BA0460B43812AAEF5F32C034FE398F25CF343974308B72",
          "CounterSignature": null,
          "ParentId": null,
          "SignatureFormat": "PAdES-BASELINE-B",
          "ExtensionPeriodMin": "2021-03-09T21:31:15",
          "ExtensionPeriodMax": "2022-08-10T07:53:38"
        }
      },
      {
        "Signature": {
          "SigningTime": "2021-03-07T12:24:56",
          "BestSignatureTime": "2021-03-09T21:31:14",
          "SignedBy": "Test certificate Dia",
          "SignatureLevel": {
            "value": "AdESig-QC",
            "description": "Advanced Electronic Signature supported by a Qualified Certificate"
          },
          "SignatureScope": [
            {
              "value": "The document ByteRange : [0, 43666, 59716, 11092]",
              "name": "Partial PDF",
              "scope": "PARTIAL"
            }
          ],
          "Filename": null,
          "CertificateChain": {
            "Certificate": [
              {
                "id": "C-F58AC656E1F9B00EFB2293962CBB8201E3F75FDB099B52B92A67D2D8BC92BCCF",
                "qualifiedName": "Test certificate Dia"
              },
              {
                "id": "C-73B2E40CFEA79BD5CF9F6B100EC8262DE4B31499C80BD7DF12BC686C3B6F0B6B",
                "qualifiedName": "\"DIIA\". Qualified Trust Services Provider"
              },
              {
                "id": "C-944F1E01408F0FD0A20820BCB92044971E5F15AC5DC69871149BFCD0BBF3016D",
                "qualifiedName": "Central certification authority"
              }
            ]
          },
          "Indication": "TOTAL_PASSED",
          "SubIndication": null,
          "Errors": [],
          "Warnings": [
            "The private key does not reside in a QSCD at issuance time!",
            "The private key does not reside in a QSCD at (best) signing time!"
          ],
          "Infos": [],
          "Id": "S-131D7B06B9B3701FB55F30EB4D6BFB851014EF46643FDF69103E284BBC95670A",
          "CounterSignature": null,
          "ParentId": null,
          "SignatureFormat": "PAdES-BASELINE-B",
          "ExtensionPeriodMin": "2021-03-09T21:31:15",
          "ExtensionPeriodMax": "2022-08-10T07:53:38"
        }
      },
      {
        "Signature": {
          "SigningTime": "2021-03-07T12:25:27",
          "BestSignatureTime": "2021-03-09T21:31:14",
          "SignedBy": "Test certificate Dia",
          "SignatureLevel": {
            "value": "AdESig-QC",
            "description": "Advanced Electronic Signature supported by a Qualified Certificate"
          },
          "SignatureScope": [
            {
              "value": "The document ByteRange : [0, 73722, 89772, 4146]",
              "name": "Partial PDF",
              "scope": "PARTIAL"
            }
          ],
          "Filename": null,
          "CertificateChain": {
            "Certificate": [
              {
                "id": "C-F58AC656E1F9B00EFB2293962CBB8201E3F75FDB099B52B92A67D2D8BC92BCCF",
                "qualifiedName": "Test certificate Dia"
              },
              {
                "id": "C-73B2E40CFEA79BD5CF9F6B100EC8262DE4B31499C80BD7DF12BC686C3B6F0B6B",
                "qualifiedName": "\"DIIA\". Qualified Trust Services Provider"
              },
              {
                "id": "C-944F1E01408F0FD0A20820BCB92044971E5F15AC5DC69871149BFCD0BBF3016D",
                "qualifiedName": "Central certification authority"
              }
            ]
          },
          "Indication": "TOTAL_PASSED",
          "SubIndication": null,
          "Errors": [],
          "Warnings": [
            "The private key does not reside in a QSCD at issuance time!",
            "The private key does not reside in a QSCD at (best) signing time!"
          ],
          "Infos": [],
          "Id": "S-DA8AABF8C510D97695BE6C853D2B472B557B5AF7A721223C632CE18B414C7A8F",
          "CounterSignature": null,
          "ParentId": null,
          "SignatureFormat": "PAdES-BASELINE-B",
          "ExtensionPeriodMin": "2021-03-09T21:31:15",
          "ExtensionPeriodMax": "2022-08-10T07:53:38"
        }
      },
      {
        "Signature": {
          "SigningTime": "2021-03-07T12:25:43",
          "BestSignatureTime": "2021-03-09T21:31:14",
          "SignedBy": "Test certificate Dia",
          "SignatureLevel": {
            "value": "AdESig-QC",
            "description": "Advanced Electronic Signature supported by a Qualified Certificate"
          },
          "SignatureScope": [
            {
              "value": "Full document",
              "name": "Full PDF",
              "scope": "FULL"
            }
          ],
          "Filename": null,
          "CertificateChain": {
            "Certificate": [
              {
                "id": "C-F58AC656E1F9B00EFB2293962CBB8201E3F75FDB099B52B92A67D2D8BC92BCCF",
                "qualifiedName": "Test certificate Dia"
              },
              {
                "id": "C-73B2E40CFEA79BD5CF9F6B100EC8262DE4B31499C80BD7DF12BC686C3B6F0B6B",
                "qualifiedName": "\"DIIA\". Qualified Trust Services Provider"
              },
              {
                "id": "C-944F1E01408F0FD0A20820BCB92044971E5F15AC5DC69871149BFCD0BBF3016D",
                "qualifiedName": "Central certification authority"
              }
            ]
          },
          "Indication": "TOTAL_PASSED",
          "SubIndication": null,
          "Errors": [],
          "Warnings": [
            "The private key does not reside in a QSCD at issuance time!",
            "The private key does not reside in a QSCD at (best) signing time!"
          ],
          "Infos": [],
          "Id": "S-735F3A470E4288AE72C11CED0FFC7062F2E6B24BF0F84711FFBE4FDCB4E189D1",
          "CounterSignature": null,
          "ParentId": null,
          "SignatureFormat": "PAdES-BASELINE-B",
          "ExtensionPeriodMin": "2021-03-09T21:31:15",
          "ExtensionPeriodMax": "2022-08-10T07:53:38"
        }
      }
    ],
    "Semantic": null,
    "ValidationTime": "2021-03-09T21:31:14"
  }
}
